COPYING
INSTALL
README
setup.py
examples/test_widgets.py
pygu/__init__.py
pygu/common.py
pygu/pms.py
pygu/pygw.py
pygu/pyramid.py
pygu/pyslim.py
pygu.egg-info/PKG-INFO
pygu.egg-info/SOURCES.txt
pygu.egg-info/dependency_links.txt
pygu.egg-info/top_level.txt