Metadata-Version: 1.0
Name: pygu
Version: 4.2.2
Summary: Pydsigner's Pygame Utilities - a collection of handy modules for Pygame.
Home-page: http://github.com/pydsigner/pygu
Author: Daniel Foerster/pydsigner
Author-email: pydsigner@gmail.com
License: LGPLv3
Platform: UNKNOWN
Classifier: Development Status :: 4 - Beta
Classifier: Intended Audience :: Developers
Classifier: Operating System :: MacOS :: MacOS X
Classifier: Operating System :: Microsoft :: Windows
Classifier: Operating System :: POSIX
Classifier: Programming Language :: Python
